jitanalyzer/__init__.py
jitanalyzer/core.py
pyarmor_runtime_000000/__init__.py
pyarmor_runtime_000000/pyarmor_runtime.pyd
jitanalyzer-0.1.1.dist-info/METADATA
jitanalyzer-0.1.1.dist-info/WHEEL
jitanalyzer-0.1.1.dist-info/top_level.txt
jitanalyzer-0.1.1.dist-info/RECORD
