Metadata-Version: 2.4
Name: jitanalyzer
Version: 0.1.1
Summary: Generate HTML and PDF EDA reports from Excel files
Author: JIT
Classifier: Programming Language :: Python :: 3
Requires-Python: >=3.6
Requires-Dist: pandas
Requires-Dist: numpy
Requires-Dist: plotly
Requires-Dist: pdfkit
Requires-Dist: openpyxl
Requires-Dist: scipy
Requires-Dist: matplotlib
Requires-Dist: statsmodels
Requires-Dist: jinja2
Dynamic: author
Dynamic: classifier
Dynamic: requires-dist
Dynamic: requires-python
Dynamic: summary
